tree/__init__.py
tree/__main__.py
tree/_gentree.py
tree/tree_exc.py
tree/tree_format.py
tree/tree_parser.py
utree-0.1.0.dist-info/licenses/LICENSE
utree-0.1.0.dist-info/METADATA
utree-0.1.0.dist-info/WHEEL
utree-0.1.0.dist-info/entry_points.txt
utree-0.1.0.dist-info/top_level.txt
utree-0.1.0.dist-info/RECORD
