Metadata-Version: 2.4
Name: utree
Version: 0.1.0
Summary: Pure-Python Implementation of tree commandline utility
Author-email: Dmytro Yaroshenko <thehelixpg@gmail.com>
License: The MIT License (MIT)
Project-URL: Homepage, https://github.com/hbmartin/tree
Project-URL: Bug Reports, https://github.com/hbmartin/tree/issues
Project-URL: Source, https://github.com/hbmartin/tree
Keywords: python,tree,commandline
Classifier: Intended Audience :: Developers
Classifier: Natural Language :: English
Classifier: Programming Language :: Python
Classifier: Topic :: Software Development :: Libraries :: Python Modules
Classifier: Programming Language :: Python :: 3
Classifier: Programming Language :: Python :: 3 :: Only
Classifier: Programming Language :: Python :: 3.9
Classifier: Programming Language :: Python :: 3.10
Classifier: Programming Language :: Python :: 3.11
Classifier: Programming Language :: Python :: 3.12
Classifier: Programming Language :: Python :: 3.13
Classifier: Programming Language :: Python :: Implementation :: CPython
Requires-Python: >=3.9
License-File: LICENSE
Dynamic: license-file
